namdevel/__init__.py
namdevel/ipgeo.py
ipgeo_namdevel-0.0.1.dist-info/LICENSE
ipgeo_namdevel-0.0.1.dist-info/METADATA
ipgeo_namdevel-0.0.1.dist-info/WHEEL
ipgeo_namdevel-0.0.1.dist-info/top_level.txt
ipgeo_namdevel-0.0.1.dist-info/RECORD
