Metadata-Version: 2.1
Name: ipgeo-namdevel
Version: 0.0.1
Summary: Free IP Geolocation API and IP Location Lookup
Home-page: https://github.com/namdevel/ipgeo
Author: namdevel
Author-email: namdevel@gmail.com
License: UNKNOWN
Project-URL: Bug Tracker, https://github.com/namdevel/ipgeo/issues
Platform: UNKNOWN
Classifier: Programming Language :: Python :: 3
Classifier: License :: OSI Approved :: MIT License
Classifier: Operating System :: OS Independent
Requires-Python: >=3.6
License-File: LICENSE
